st_draggable_list/__init__.py
st_draggable_list/frontend/.env
st_draggable_list/frontend/.prettierrc
st_draggable_list/frontend/package.json
st_draggable_list/frontend/tsconfig.json
st_draggable_list/frontend/yarn.lock
st_draggable_list/frontend/.storybook/main.js
st_draggable_list/frontend/.storybook/preview.js
st_draggable_list/frontend/build/asset-manifest.json
st_draggable_list/frontend/build/bootstrap.min.css
st_draggable_list/frontend/build/index.html
st_draggable_list/frontend/build/static/js/2.16b7114b.chunk.js
st_draggable_list/frontend/build/static/js/2.16b7114b.chunk.js.LICENSE.txt
st_draggable_list/frontend/build/static/js/2.16b7114b.chunk.js.map
st_draggable_list/frontend/build/static/js/2.f19ef9f8.chunk.js
st_draggable_list/frontend/build/static/js/2.f19ef9f8.chunk.js.LICENSE.txt
st_draggable_list/frontend/build/static/js/2.f19ef9f8.chunk.js.map
st_draggable_list/frontend/build/static/js/main.286b073e.chunk.js
st_draggable_list/frontend/build/static/js/main.286b073e.chunk.js.map
st_draggable_list/frontend/build/static/js/main.a1adb3d1.chunk.js
st_draggable_list/frontend/build/static/js/main.a1adb3d1.chunk.js.map
st_draggable_list/frontend/build/static/js/runtime-main.6c2dc79e.js
st_draggable_list/frontend/build/static/js/runtime-main.6c2dc79e.js.map
st_draggable_list/frontend/public/bootstrap.min.css
st_draggable_list/frontend/public/index.html
st_draggable_list/frontend/src/DraggableList.tsx
st_draggable_list/frontend/src/index.tsx
st_draggable_list/frontend/src/react-app-env.d.ts
st_draggable_list/frontend/stories/DraggableList.stories.tsx
streamlit_draggable_list-0.0.1.dist-info/LICENSE
streamlit_draggable_list-0.0.1.dist-info/METADATA
streamlit_draggable_list-0.0.1.dist-info/WHEEL
streamlit_draggable_list-0.0.1.dist-info/top_level.txt
streamlit_draggable_list-0.0.1.dist-info/RECORD
