Metadata-Version: 2.1
Name: streamlit-draggable-list
Version: 0.0.1
Summary: Streamlit component of draggable list
Home-page: 
Author: tk42
Author-email: nsplat+pip@gmail.com
Requires-Python: >=3.6
License-File: LICENSE
Requires-Dist: streamlit (>=0.63)
